[
	{
		"inputs": [],
		"payable": false,
		"stateMutability": "nonpayable",
		"type": "constructor"
	},
	{
		"constant": true,
		"inputs": [],
		"name": "getInfo",
		"outputs": [
			{
				"internalType": "address",
				"name": "",
				"type": "address"
			},
			{
				"internalType": "string",
				"name": "",
				"type": "string"
			}
		],
		"payable": false,
		"stateMutability": "view",
		"type": "function"
	},
	{
		"constant": false,
		"inputs": [
			{
				"internalType": "address",
				"name": "_sender",
				"type": "address"
			},
			{
				"internalType": "string",
				"name": "_content",
				"type": "string"
			}
		],
		"name": "makeProposal",
		"outputs": [],
		"payable": false,
		"stateMutability": "nonpayable",
		"type": "function"
	},
	{
		"constant": true,
		"inputs": [],
		"name": "proposal",
		"outputs": [
			{
				"internalType": "address",
				"name": "sender",
				"type": "address"
			},
			{
				"internalType": "string",
				"name": "content",
				"type": "string"
			}
		],
		"payable": false,
		"stateMutability": "view",
		"type": "function"
	}
]